cmdwrap/__init__.py
cmdwrap/main.py
cmdwrap/meta.py
cmdwrap/cli/__init__.py
cmdwrap/cli/wrap.py
cmdwrap-0.1.1.dist-info/LICENSE
cmdwrap-0.1.1.dist-info/METADATA
cmdwrap-0.1.1.dist-info/WHEEL
cmdwrap-0.1.1.dist-info/entry_points.txt
cmdwrap-0.1.1.dist-info/top_level.txt
cmdwrap-0.1.1.dist-info/RECORD
